README.rst
setup.py
django_shop/__init__.py
django_shop/admin.py
django_shop/admin_forms.py
django_shop/apps.py
django_shop/cart.py
django_shop/context_processors.py
django_shop/errors.py
django_shop/fields.py
django_shop/forms.py
django_shop/models.py
django_shop/signals.py
django_shop/urls.py
django_shop/views.py
django_shop/migrations/0001_initial.py
django_shop/migrations/0002_auto_20160807_1222.py
django_shop/migrations/0003_auto_20160809_2227.py
django_shop/migrations/0004_auto_20160813_1439.py
django_shop/migrations/0005_auto_20160813_1439.py
django_shop/migrations/0006_auto_20160813_1708.py
django_shop/migrations/0007_auto_20160813_2129.py
django_shop/migrations/0008_auto_20160817_1500.py
django_shop/migrations/0009_auto_20160818_1659.py
django_shop/migrations/0010_auto_20160820_1240.py
django_shop/migrations/0011_auto_20160820_1301.py
django_shop/migrations/0012_productorder_stock_price.py
django_shop/migrations/0013_auto_20161217_1739.py
django_shop/migrations/0014_auto_20161217_1741.py
django_shop/migrations/0015_auto_20170106_2024.py
django_shop/migrations/0016_auto_20170210_2125.py
django_shop/migrations/0017_auto_20170213_2243.py
django_shop/migrations/0018_auto_20170216_2151.py
django_shop/migrations/0019_auto_20170226_1318.py
django_shop/migrations/0020_auto_20170304_1349.py
django_shop/migrations/0021_auto_20170402_2130.py
django_shop/migrations/0022_auto_20170404_2136.py
django_shop/migrations/0023_auto_20170406_2157.py
django_shop/migrations/0024_auto_20170902_1331.py
django_shop/migrations/0025_auto_20170902_1752.py
django_shop/migrations/__init__.py
django_shop/templatetags/__init__.py
django_shop/templatetags/shop_helpers.py
django_shop/tests/__init__.py
django_shop/tests/runtests.py
django_shop/tests/test_cart.py
django_shop/tests/test_forms.py
django_shop/tests/test_models.py
django_shop/tests/test_views.py
django_shop/tests/urls.py
django_shop/utils/__init__.py
django_shop/utils/delivery.py
django_shop/utils/hooks.py
django_simple_shop.egg-info/PKG-INFO
django_simple_shop.egg-info/SOURCES.txt
django_simple_shop.egg-info/dependency_links.txt
django_simple_shop.egg-info/not-zip-safe
django_simple_shop.egg-info/requires.txt
django_simple_shop.egg-info/top_level.txt